sphinx_pydantic_sqlalchemy/__init__.py
sphinx_pydantic_sqlalchemy-0.1.1.dist-info/WHEEL
sphinx_pydantic_sqlalchemy-0.1.1.dist-info/METADATA
sphinx_pydantic_sqlalchemy-0.1.1.dist-info/RECORD
